MANIFEST.in
setup.py
dagobah/__init__.py
dagobah.egg-info/PKG-INFO
dagobah.egg-info/SOURCES.txt
dagobah.egg-info/dependency_links.txt
dagobah.egg-info/entry_points.txt
dagobah.egg-info/not-zip-safe
dagobah.egg-info/requires.txt
dagobah.egg-info/top_level.txt
dagobah/backend/__init__.py
dagobah/backend/alembic.ini
dagobah/backend/base.py
dagobah/backend/mongo.py
dagobah/backend/sqlite.py
dagobah/backend/sqlite_models.py
dagobah/backend/migrations/README
dagobah/backend/migrations/__init__.py
dagobah/backend/migrations/__init__.pyc
dagobah/backend/migrations/env.py
dagobah/backend/migrations/env.pyc
dagobah/backend/migrations/script.py.mako
dagobah/backend/migrations/versions/2ab7af991b87_v0_2.py
dagobah/backend/migrations/versions/2ab7af991b87_v0_2.pyc
dagobah/backend/migrations/versions/4de8f69a75d1_adding_notes_column.py
dagobah/backend/migrations/versions/4de8f69a75d1_adding_notes_column.pyc
dagobah/backend/migrations/versions/d455481ec6e4_adding_hostname.py
dagobah/backend/migrations/versions/d455481ec6e4_adding_hostname.pyc
dagobah/core/__init__.py
dagobah/core/components.py
dagobah/core/core.py
dagobah/core/dag.py
dagobah/daemon/__init__.py
dagobah/daemon/api.py
dagobah/daemon/app.py
dagobah/daemon/auth.py
dagobah/daemon/daemon.py
dagobah/daemon/dagobahd.yml
dagobah/daemon/util.py
dagobah/daemon/views.py
dagobah/daemon/static/.gitignore
dagobah/daemon/static/css/job_detail.css
dagobah/daemon/static/css/job_graph.css
dagobah/daemon/static/css/jobs.css
dagobah/daemon/static/css/kickstrap.css
dagobah/daemon/static/css/log_detail.css
dagobah/daemon/static/css/login.css
dagobah/daemon/static/css/settings.css
dagobah/daemon/static/css/site.css
dagobah/daemon/static/css/task_detail.css
dagobah/daemon/static/img/favicon.ico
dagobah/daemon/static/js/job_detail.js
dagobah/daemon/static/js/job_graph.js
dagobah/daemon/static/js/job_model.js
dagobah/daemon/static/js/jobs.js
dagobah/daemon/static/js/log_detail.js
dagobah/daemon/static/js/navbar.js
dagobah/daemon/static/js/settings.js
dagobah/daemon/static/js/site.js
dagobah/daemon/static/js/task_detail.js
dagobah/daemon/static/lib/d3.v3.min.js
dagobah/daemon/static/lib/handlebars.js
dagobah/daemon/static/lib/moment.min.js
