Metadata-Version: 1.0
Name: dagobah
Version: 0.3.0
Summary: Simple DAG-based job scheduler
Home-page: http://github.com/tthieman/dagobah
Author: Travis Thieman
Author-email: travis.thieman@gmail.com
License: WTFPL
Platform: UNKNOWN
